Metadata-Version: 2.1
Name: mozilla-jsoncache
Version: 0.1.5
Summary: JSON Cache Loader
Home-page: https://github.com/mozilla/jsoncache
Author: Mozilla Corporation
Author-email: vng@mozilla.org
License: MPL 2.0
Platform: UNKNOWN
Classifier: Development Status :: 3 - Alpha
Classifier: Environment :: Web Environment :: Mozilla
Classifier: Intended Audience :: Developers
Classifier: License :: OSI Approved :: Mozilla Public License 2.0 (MPL 2.0)
Classifier: Programming Language :: Python
Classifier: Programming Language :: Python :: 3
Classifier: Programming Language :: Python :: 3.7
